dataknobs_bots/__init__.py
dataknobs_bots/py.typed
dataknobs_bots/api/__init__.py
dataknobs_bots/api/dependencies.py
dataknobs_bots/api/exceptions.py
dataknobs_bots/artifacts/__init__.py
dataknobs_bots/artifacts/models.py
dataknobs_bots/artifacts/registry.py
dataknobs_bots/artifacts/tools.py
dataknobs_bots/bot/__init__.py
dataknobs_bots/bot/base.py
dataknobs_bots/bot/context.py
dataknobs_bots/bot/manager.py
dataknobs_bots/bot/registry.py
dataknobs_bots/config/__init__.py
dataknobs_bots/config/resolution.py
dataknobs_bots/config/versioning.py
dataknobs_bots/context/__init__.py
dataknobs_bots/context/accumulator.py
dataknobs_bots/context/builder.py
dataknobs_bots/knowledge/__init__.py
dataknobs_bots/knowledge/ingestion.py
dataknobs_bots/knowledge/rag.py
dataknobs_bots/knowledge/registry_mixin.py
dataknobs_bots/knowledge/service.py
dataknobs_bots/knowledge/query/__init__.py
dataknobs_bots/knowledge/query/expander.py
dataknobs_bots/knowledge/query/transformer.py
dataknobs_bots/knowledge/retrieval/__init__.py
dataknobs_bots/knowledge/retrieval/formatter.py
dataknobs_bots/knowledge/retrieval/merger.py
dataknobs_bots/knowledge/storage/__init__.py
dataknobs_bots/knowledge/storage/backend.py
dataknobs_bots/knowledge/storage/file.py
dataknobs_bots/knowledge/storage/memory.py
dataknobs_bots/knowledge/storage/models.py
dataknobs_bots/knowledge/storage/s3.py
dataknobs_bots/memory/__init__.py
dataknobs_bots/memory/base.py
dataknobs_bots/memory/buffer.py
dataknobs_bots/memory/vector.py
dataknobs_bots/middleware/__init__.py
dataknobs_bots/middleware/base.py
dataknobs_bots/middleware/cost.py
dataknobs_bots/middleware/logging.py
dataknobs_bots/reasoning/__init__.py
dataknobs_bots/reasoning/base.py
dataknobs_bots/reasoning/focus_guard.py
dataknobs_bots/reasoning/function_resolver.py
dataknobs_bots/reasoning/observability.py
dataknobs_bots/reasoning/react.py
dataknobs_bots/reasoning/simple.py
dataknobs_bots/reasoning/task_injection.py
dataknobs_bots/reasoning/wizard.py
dataknobs_bots-0.4.1.dist-info/METADATA
dataknobs_bots-0.4.1.dist-info/WHEEL
dataknobs_bots-0.4.1.dist-info/RECORD
