Metadata-Version: 2.4
Name: dataknobs-bots
Version: 0.4.1
Summary: Configuration-driven AI agents for DataKnobs
Author-email: Spence Koehler <KoehlerSB747@gmail.com>
Requires-Python: >=3.10
Requires-Dist: dataknobs-common>=1.0.1
Requires-Dist: dataknobs-config>=0.2.0
Requires-Dist: dataknobs-data>=0.3.1
Requires-Dist: dataknobs-fsm>=0.1.2
Requires-Dist: dataknobs-llm>=0.1.0
Requires-Dist: dataknobs-xization>=1.1.0
